mt5/__init__.py
mt5/account.py
mt5/order.py
tests/__init__.py
tests/context.py
tests/test_accounts.py
mt5_lite-0.0.7.dist-info/LICENCE
mt5_lite-0.0.7.dist-info/METADATA
mt5_lite-0.0.7.dist-info/WHEEL
mt5_lite-0.0.7.dist-info/top_level.txt
mt5_lite-0.0.7.dist-info/RECORD
